stylelens_search_vector
