Metadata-Version: 1.0
Name: stylelens-search-vector
Version: 1.0.10
Summary: stylelens-search-vector
Home-page: UNKNOWN
Author: UNKNOWN
Author-email: bluehackmaster@bluehack.net
License: UNKNOWN
Keywords: BlueLens,stylelens-search-vector
Platform: UNKNOWN
